.pre-commit-config.yaml
CLA.md
CONTRIBUTING.md
LICENSE
MANIFEST.in
README.md
mypy.ini
pyproject.toml
setup.cfg
setup.py
tox.ini
versioneer.py
_images/DP_DDP_perf.png
_images/nlp_x_recsys.png
_images/pipeline.png
_images/preproc_data_example.png
_images/sequential_rec.png
_images/transformers4rec_metaarchitecture.png
merlin_standard_lib/__init__.py
merlin_standard_lib/proto/__init__.py
merlin_standard_lib/proto/schema_bp.py
merlin_standard_lib/schema/__init__.py
merlin_standard_lib/schema/schema.py
merlin_standard_lib/schema/tag.py
merlin_standard_lib/utils/__init__.py
merlin_standard_lib/utils/embedding_utils.py
requirements/base_external.txt
requirements/base_merlin.txt
requirements/dev.txt
requirements/docs.txt
requirements/nvtabular.txt
requirements/pytorch.txt
requirements/test.txt
tests/__init__.py
tests/conftest.py
tests/integration/notebooks/test_end_to_end_session_based.py
tests/integration/notebooks/test_getting_started_session_based.py
tests/integration/notebooks/test_notebooks.py
tests/unit/__init__.py
tests/unit/assets/schema.pbtxt
tests/unit/assets/data_schema/data.parquet
tests/unit/assets/data_schema/data_schema.pbtxt
tests/unit/assets/data_schema/data_seq.parquet
tests/unit/assets/data_schema/data_seq_schema.pbtxt
tests/unit/config/__init__.py
tests/unit/config/test_schema.py
tests/unit/config/test_trainer.py
tests/unit/config/test_transformer.py
tests/unit/data/__init__.py
tests/unit/data/test_synthetic.py
tests/unit/data/testing/__init__.py
tests/unit/data/testing/test_dataset.py
tests/unit/data/testing/tabular_data/__init__.py
tests/unit/data/testing/tabular_data/test_dataset.py
tests/unit/merlin_standard_lib/__init__.py
tests/unit/merlin_standard_lib/schema/__init__.py
tests/unit/merlin_standard_lib/schema/test_schema.py
tests/unit/torch/__init__.py
tests/unit/torch/_conftest.py
tests/unit/torch/test_dataloader_utils.py
tests/unit/torch/test_experimental.py
tests/unit/torch/test_losses.py
tests/unit/torch/test_masking.py
transformers4rec.egg-info/PKG-INFO
transformers4rec.egg-info/SOURCES.txt
transformers4rec.egg-info/dependency_links.txt
transformers4rec.egg-info/requires.txt
transformers4rec.egg-info/top_level.txt
