Metadata-Version: 2.1
Name: transformers4rec
Version: 23.12.0
Summary: UNKNOWN
Home-page: https://github.com/NVIDIA-Merlin/Transformers4Rec
Author: NVIDIA Corporation
License: Apache 2.0
Platform: UNKNOWN
Classifier: Development Status :: 4 - Beta
Classifier: Programming Language :: Python :: 3
Classifier: Intended Audience :: Developers
Classifier: License :: OSI Approved :: Apache Software License
Classifier: Topic :: Software Development :: Libraries
Classifier: Topic :: Scientific/Engineering
Provides-Extra: base
Provides-Extra: pytorch
Provides-Extra: nvtabular
Provides-Extra: docs
Provides-Extra: dev
Provides-Extra: all
License-File: LICENSE
